{
  "subjects": [
    {
      "id": 1,
      "category": "Web Development",
      "name": "React & TypeScript",
      "description": "Master React with TypeScript for modern apps",
      "hoursDone": 26,
      "totalHours": 40,
      "status": "In Progress"
    },
    {
      "id": 2,
      "category": "Language",
      "name": "Spanish Language",
      "description": "Learn conversational Spanish for communication",
      "hoursDone": 30,
      "totalHours": 100,
      "status": "In Progress"
    },
    {
      "id": 3,
      "category": "Programming",
      "name": "JavaScript Mastery",
      "description": "Deep dive into modern JavaScript",
      "hoursDone": 50,
      "totalHours": 50,
      "status": "Completed"
    },
    {
      "id": 4,
      "category": "Design",
      "name": "Graphic Design Basics",
      "description": "Figma, Canva and branding fundamentals",
      "hoursDone": 18,
      "totalHours": 60,
      "status": "In Progress"
    },
    {
      "id": 5,
      "category": "Data Analysis",
      "name": "Excel & Power BI",
      "description": "Visualize data and build dashboards",
      "hoursDone": 40,
      "totalHours": 40,
      "status": "Completed"
    }
  ]
}
